pyDigitalWaveTools/__init__.py
pyDigitalWaveTools/json/__init__.py
pyDigitalWaveTools/json/value_format.py
pyDigitalWaveTools/json/writer.py
pyDigitalWaveTools/vcd/__init__.py
pyDigitalWaveTools/vcd/common.py
pyDigitalWaveTools/vcd/parser.py
pyDigitalWaveTools/vcd/value_format.py
pyDigitalWaveTools/vcd/writer.py
pyDigitalWaveTools-1.1.dist-info/LICENSE
pyDigitalWaveTools-1.1.dist-info/METADATA
pyDigitalWaveTools-1.1.dist-info/WHEEL
pyDigitalWaveTools-1.1.dist-info/top_level.txt
pyDigitalWaveTools-1.1.dist-info/zip-safe
pyDigitalWaveTools-1.1.dist-info/RECORD
