Metadata-Version: 2.1
Name: pyDigitalWaveTools
Version: 1.1
Summary: Library for operations with VCD and other digital wave files
Home-page: https://github.com/Nic30/pyDigitalWaveTools
Author: Michal Orsak
Author-email: Nic30original@gmail.com
License: MIT
Platform: UNKNOWN
Classifier: Development Status :: 4 - Beta
Classifier: Intended Audience :: Developers
Classifier: License :: OSI Approved :: MIT License
Classifier: Operating System :: OS Independent
Classifier: Programming Language :: Python :: 3
Classifier: Topic :: Scientific/Engineering :: Electronic Design Automation (EDA)
Classifier: Topic :: System :: Hardware
Classifier: Topic :: System :: Emulators
Classifier: Topic :: Utilities
License-File: LICENSE
